{"1": {"2016092513": {"home": 19, "away": 23}, "2016092512": {"home": 11, "away": 44}, "2016092511": {"home": 8, "away": 18}, "2016092200": {"home": 19, "away": 26}, "2016092510": {"home": 43, "away": 12}, "2016092600": {"home": 31, "away": 16}, "2016092509": {"home": 2, "away": 32}, "2016092508": {"home": 2, "away": 28}, "2016092507": {"home": 33, "away": 34}, "2016092506": {"home": 30, "away": 6}, "2016092505": {"home": 16, "away": 12}, "2016092504": {"home": 27, "away": 29}, "2016092503": {"home": 45, "away": 1}, "2016092502": {"home": 0, "away": 17}, "2016092501": {"home": 0, "away": 26}, "2016092500": {"home": 38, "away": 3}}, "0": {"2016092513": {"home": 42, "away": 16}, "2016092512": {"home": 9, "away": 19}, "2016092511": {"home": 42, "away": 12}, "2016092200": {"home": 4, "away": 2}, "2016092510": {"home": 31, "away": 6}, "2016092600": {"home": 9, "away": 44}, "2016092509": {"home": 26, "away": 23}, "2016092508": {"home": 21, "away": 33}, "2016092507": {"home": 32, "away": 13}, "2016092506": {"home": 33, "away": 43}, "2016092505": {"home": 5, "away": 20}, "2016092504": {"home": 37, "away": 19}, "2016092503": {"home": 45, "away": 14}, "2016092502": {"home": 13, "away": 32}, "2016092501": {"home": 32, "away": 7}, "2016092500": {"home": 28, "away": 38}}, "3": {"2016092513": {"home": 36, "away": 18}, "2016092512": {"home": 26, "away": 44}, "2016092511": {"home": 35, "away": 0}, "2016092200": {"home": 19, "away": 22}, "2016092510": {"home": 9, "away": 5}, "2016092600": {"home": 22, "away": 2}, "2016092509": {"home": 16, "away": 26}, "2016092508": {"home": 10, "away": 25}, "2016092507": {"home": 25, "away": 9}, "2016092506": {"home": 38, "away": 27}, "2016092505": {"home": 28, "away": 39}, "2016092504": {"home": 45, "away": 19}, "2016092503": {"home": 25, "away": 25}, "2016092502": {"home": 9, "away": 29}, "2016092501": {"home": 15, "away": 39}, "2016092500": {"home": 15, "away": 13}}, "2": {"2016092513": {"home": 39, "away": 6}, "2016092512": {"home": 7, "away": 6}, "2016092511": {"home": 21, "away": 30}, "2016092200": {"home": 41, "away": 36}, "2016092510": {"home": 25, "away": 13}, "2016092600": {"home": 5, "away": 42}, "2016092509": {"home": 20, "away": 14}, "2016092508": {"home": 4, "away": 6}, "2016092507": {"home": 2, "away": 3}, "2016092506": {"home": 32, "away": 34}, "2016092505": {"home": 30, "away": 26}, "2016092504": {"home": 23, "away": 29}, "2016092503": {"home": 7, "away": 21}, "2016092502": {"home": 32, "away": 32}, "2016092501": {"home": 3, "away": 12}, "2016092500": {"home": 27, "away": 13}}, "5": {"2016092513": {"home": 19, "away": 19}, "2016092512": {"home": 12, "away": 22}, "2016092511": {"home": 41, "away": 9}, "2016092200": {"home": 24, "away": 9}, "2016092510": {"home": 14, "away": 7}, "2016092600": {"home": 7, "away": 24}, "2016092509": {"home": 16, "away": 18}, "2016092508": {"home": 4, "away": 16}, "2016092507": {"home": 9, "away": 12}, "2016092506": {"home": 37, "away": 25}, "2016092505": {"home": 6, "away": 13}, "2016092504": {"home": 12, "away": 13}, "2016092503": {"home": 32, "away": 8}, "2016092502": {"home": 35, "away": 19}, "2016092501": {"home": 16, "away": 39}, "2016092500": {"home": 20, "away": 34}}, "4": {"2016092513": {"home": 41, "away": 28}, "2016092512": {"home": 39, "away": 15}, "2016092511": {"home": 18, "away": 24}, "2016092200": {"home": 4, "away": 19}, "2016092510": {"home": 0, "away": 30}, "2016092600": {"home": 19, "away": 22}, "2016092509": {"home": 12, "away": 24}, "2016092508": {"home": 0, "away": 24}, "2016092507": {"home": 19, "away": 27}, "2016092506": {"home": 13, "away": 39}, "2016092505": {"home": 5, "away": 5}, "2016092504": {"home": 34, "away": 45}, "2016092503": {"home": 19, "away": 2}, "2016092502": {"home": 3, "away": 16}, "2016092501": {"home": 38, "away": 39}, "2016092500": {"home": 11, "away": 38}}, "7": {"2016092513": {"home": 33, "away": 12}, "2016092512": {"home": 20, "away": 29}, "2016092511": {"home": 14, "away": 3}, "2016092200": {"home": 14, "away": 7}, "2016092510": {"home": 26, "away": 34}, "2016092600": {"home": 13, "away": 21}, "2016092509": {"home": 25, "away": 15}, "2016092508": {"home": 20, "away": 10}, "2016092507": {"home": 44, "away": 8}, "2016092506": {"home": 27, "away": 23}, "2016092505": {"home": 33, "away": 12}, "2016092504": {"home": 28, "away": 26}, "2016092503": {"home": 25, "away": 3}, "2016092502": {"home": 0, "away": 32}, "2016092501": {"home": 38, "away": 17}, "2016092500": {"home": 31, "away": 17}}, "6": {"2016092513": {"home": 19, "away": 1}, "2016092512": {"home": 10, "away": 23}, "2016092511": {"home": 37, "away": 25}, "2016092200": {"home": 13, "away": 31}, "2016092510": {"home": 5, "away": 7}, "2016092600": {"home": 35, "away": 45}, "2016092509": {"home": 0, "away": 15}, "2016092508": {"home": 16, "away": 0}, "2016092507": {"home": 24, "away": 25}, "2016092506": {"home": 16, "away": 10}, "2016092505": {"home": 33, "away": 15}, "2016092504": {"home": 15, "away": 34}, "2016092503": {"home": 3, "away": 39}, "2016092502": {"home": 4, "away": 7}, "2016092501": {"home": 10, "away": 9}, "2016092500": {"home": 28, "away": 28}}, "9": {"2016092513": {"home": 1, "away": 33}, "2016092512": {"home": 37, "away": 21}, "2016092511": {"home": 18, "away": 3}, "2016092200": {"home": 6, "away": 28}, "2016092510": {"home": 27, "away": 34}, "2016092600": {"home": 23, "away": 36}, "2016092509": {"home": 33, "away": 45}, "2016092508": {"home": 45, "away": 19}, "2016092507": {"home": 4, "away": 34}, "2016092506": {"home": 44, "away": 4}, "2016092505": {"home": 10, "away": 14}, "2016092504": {"home": 31, "away": 13}, "2016092503": {"home": 42, "away": 41}, "2016092502": {"home": 15, "away": 37}, "2016092501": {"home": 15, "away": 42}, "2016092500": {"home": 3, "away": 12}}, "8": {"2016092513": {"home": 3, "away": 23}, "2016092512": {"home": 44, "away": 34}, "2016092511": {"home": 38, "away": 23}, "2016092200": {"home": 27, "away": 19}, "2016092510": {"home": 10, "away": 17}, "2016092600": {"home": 35, "away": 29}, "2016092509": {"home": 25, "away": 1}, "2016092508": {"home": 3, "away": 31}, "2016092507": {"home": 10, "away": 45}, "2016092506": {"home": 2, "away": 12}, "2016092505": {"home": 43, "away": 5}, "2016092504": {"home": 1, "away": 6}, "2016092503": {"home": 42, "away": 25}, "2016092502": {"home": 11, "away": 10}, "2016092501": {"home": 40, "away": 13}, "2016092500": {"home": 44, "away": 4}}}